neuralpit/services/combiner.py
neuralpit/services/loader.py
neuralpit/services/repository.py
neuralpit/services/splitter.py
neuralpit/services/storage.py
neuralpit/services/tracker.py
neuralpit/services/vectorstore.py
neuralpit/utils/code_executor.py
neuralpit/utils/data_analytic.py
neuralpit/utils/misc.py
neuralpit/utils/send_message.py
neuralpit/utils/settings.py
neuralpit/utils/webscrpper.py
neuralpit-3.5.6.dist-info/METADATA
neuralpit-3.5.6.dist-info/WHEEL
neuralpit-3.5.6.dist-info/top_level.txt
neuralpit-3.5.6.dist-info/RECORD
