Metadata-Version: 2.1
Name: neuralpit
Version: 3.5.6
Summary: NeuralPit SDK
Author-email: Quang Nguyen <quang.nguyen@neuralpit.com>
Keywords: api,neural,neuralpit
Classifier: License :: OSI Approved :: MIT License
Classifier: Programming Language :: Python
Classifier: Programming Language :: Python :: 3
Requires-Python: >=3.9
Requires-Dist: requests
Requires-Dist: langchain ==v0.0.230
Requires-Dist: lxml
Requires-Dist: openai
Requires-Dist: tiktoken
Requires-Dist: bs4
Requires-Dist: qdrant-client
Requires-Dist: boto3
Requires-Dist: PyMuPDF
Requires-Dist: unstructured[doc,docx,ppt,pptx,xls,xlsx]
Requires-Dist: email-validator
Requires-Dist: scrapy
Requires-Dist: pytube
Requires-Dist: youtube-transcript-api
Requires-Dist: pandas
Requires-Dist: numpy
Requires-Dist: astor
Requires-Dist: matplotlib
Provides-Extra: dev
Requires-Dist: black ; extra == 'dev'
Requires-Dist: bumpver ; extra == 'dev'
Requires-Dist: isort ; extra == 'dev'
Requires-Dist: pip-tools ; extra == 'dev'
Requires-Dist: pytest ; extra == 'dev'
